glutemulo/backend/__init__.py
glutemulo/backend/big_query.py
glutemulo/backend/carto.py
glutemulo/backend/logger.py
glutemulo/backend/postgres.py
glutemulo/backend/redis.py
glutemulo/backend/sql.py
glutemulo/config.py
glutemulo/consumer.py
glutemulo/errors.py
glutemulo/gluto.py
glutemulo/kafka/__init__.py
glutemulo/kafka/avro_utils.py
glutemulo/kafka/consumer.py
glutemulo/kafka/producer.py
glutemulo/logger.py
glutemulo/producer.py
geolibs_glutemulo-0.1.3.dist-info/LICENSE
geolibs_glutemulo-0.1.3.dist-info/WHEEL
geolibs_glutemulo-0.1.3.dist-info/METADATA
geolibs_glutemulo-0.1.3.dist-info/RECORD
