Metadata-Version: 2.1
Name: geolibs-glutemulo
Version: 0.1.3
Summary: GeoLibs data ingestor
License: MIT
Author: Geographica
Author-email: hello@geographica.com
Requires-Python: >=3.6,<4.0
Classifier: License :: OSI Approved :: MIT License
Classifier: Programming Language :: Python :: 3
Classifier: Programming Language :: Python :: 3.6
Classifier: Programming Language :: Python :: 3.7
Provides-Extra: carto
Provides-Extra: postgres
Provides-Extra: redis
Requires-Dist: carto (>=1.4,<2.0); extra == "carto"
Requires-Dist: environs (>=4.1,<5.0)
Requires-Dist: fastavro (>=0.21.23,<0.22.0)
Requires-Dist: google-cloud-bigquery (>=1.21,<2.0)
Requires-Dist: kafka-python (>=1.4,<2.0)
Requires-Dist: psycopg2-binary (>=2.8,<3.0); extra == "postgres"
Requires-Dist: redis (>=3.2,<4.0); extra == "redis"
